[
  {
    "ip_address": "20.192.185.64/26",
    "ip_type": "IPv4",
    "service": "EventHub.SouthIndia",
    "region": "southindia"
  },
  {
    "ip_address": "40.78.194.32/27",
    "ip_type": "IPv4",
    "service": "EventHub.SouthIndia",
    "region": "southindia"
  },
  {
    "ip_address": "52.172.119.0/24",
    "ip_type": "IPv4",
    "service": "EventHub.SouthIndia",
    "region": "southindia"
  },
  {
    "ip_address": "2603:1040:c06::240/122",
    "ip_type": "IPv6",
    "service": "EventHub.SouthIndia",
    "region": "southindia"
  },
  {
    "ip_address": "2603:1040:c06:2::/120",
    "ip_type": "IPv6",
    "service": "EventHub.SouthIndia",
    "region": "southindia"
  },
  {
    "ip_address": "2603:1040:c06:402::1c0/123",
    "ip_type": "IPv6",
    "service": "EventHub.SouthIndia",
    "region": "southindia"
  }
]