[
  {
    "ip_address": "191.233.205.16/28",
    "ip_type": "IPv4",
    "service": "AzureResourceManager.BrazilSouth",
    "region": "brazilsouth"
  },
  {
    "ip_address": "191.234.140.0/23",
    "ip_type": "IPv4",
    "service": "AzureResourceManager.BrazilSouth",
    "region": "brazilsouth"
  },
  {
    "ip_address": "191.234.158.0/23",
    "ip_type": "IPv4",
    "service": "AzureResourceManager.BrazilSouth",
    "region": "brazilsouth"
  },
  {
    "ip_address": "2603:1050:6::180/122",
    "ip_type": "IPv6",
    "service": "AzureResourceManager.BrazilSouth",
    "region": "brazilsouth"
  },
  {
    "ip_address": "2603:1050:6:402::280/122",
    "ip_type": "IPv6",
    "service": "AzureResourceManager.BrazilSouth",
    "region": "brazilsouth"
  }
]