{
  "provider": "tencent",
  "version": 8,
  "generated_date": "2026-07-16",
  "last_changed_date": "2026-07-16",
  "sources": [
    "BGP announced prefixes via RIPE NCC RIPEstat"
  ],
  "ipv4": {
    "cidrs": 3323,
    "merged_cidrs": 235,
    "addresses": 8221696
  },
  "ipv6": {
    "cidrs": 73,
    "merged_cidrs": 18,
    "addresses": 99370075594863674273323548672
  },
  "total_entries": 3396,
  "content_sha256": "100f39adad210ba4b27dc63a4e90286cac8a4b7cdbedd5e3bbaf5a45a45b1cbf",
  "license": "CC0-1.0",
  "license_url": "https://github.com/rezmoss/cloud-provider-ip-addresses/blob/main/LICENSE"
}