{
  "provider": "cachefly",
  "version": 1,
  "generated_date": "2026-07-21",
  "last_changed_date": "2026-07-12",
  "sources": [
    "https://cachefly.cachefly.net/ips/rproxy.txt"
  ],
  "ipv4": {
    "cidrs": 16,
    "merged_cidrs": 14,
    "addresses": 4096
  },
  "ipv6": {
    "cidrs": 0,
    "merged_cidrs": 0,
    "addresses": 0
  },
  "total_entries": 16,
  "content_sha256": "1f5a254b6a04e12bb64e451fc3768293c4e634c237f2a3a5897fe8a6097bb0f7",
  "license": "CC0-1.0",
  "license_url": "https://github.com/rezmoss/cloud-provider-ip-addresses/blob/main/LICENSE"
}