[
  {
    "ip_address": "2a04:4e41:500:f000::/52",
    "ip_type": "IPv6",
    "region": "LK-1"
  },
  {
    "ip_address": "2a04:4e41:1e00:f000::/52",
    "ip_type": "IPv6",
    "region": "LK-1"
  },
  {
    "ip_address": "2a04:4e41:1f01::/52",
    "ip_type": "IPv6",
    "region": "LK-1"
  },
  {
    "ip_address": "2a04:4e41:3400:2000::/52",
    "ip_type": "IPv6",
    "region": "LK-1"
  },
  {
    "ip_address": "2a04:4e41:4a00:2000::/52",
    "ip_type": "IPv6",
    "region": "LK-1"
  },
  {
    "ip_address": "2a04:4e41:5202::/52",
    "ip_type": "IPv6",
    "region": "LK-1"
  },
  {
    "ip_address": "2a04:4e41:5e01:4000::/52",
    "ip_type": "IPv6",
    "region": "LK-1"
  },
  {
    "ip_address": "2a04:4e41:7601:4000::/52",
    "ip_type": "IPv6",
    "region": "LK-1"
  },
  {
    "ip_address": "140.248.8.36/31",
    "ip_type": "IPv4",
    "region": "LK-1"
  },
  {
    "ip_address": "140.248.38.36/31",
    "ip_type": "IPv4",
    "region": "LK-1"
  },
  {
    "ip_address": "146.75.128.16/31",
    "ip_type": "IPv4",
    "region": "LK-1"
  },
  {
    "ip_address": "146.75.132.72/31",
    "ip_type": "IPv4",
    "region": "LK-1"
  },
  {
    "ip_address": "146.75.160.72/31",
    "ip_type": "IPv4",
    "region": "LK-1"
  },
  {
    "ip_address": "146.75.166.100/31",
    "ip_type": "IPv4",
    "region": "LK-1"
  },
  {
    "ip_address": "146.75.197.44/31",
    "ip_type": "IPv4",
    "region": "LK-1"
  },
  {
    "ip_address": "146.75.236.16/31",
    "ip_type": "IPv4",
    "region": "LK-1"
  }
]