[
  {
    "ip_address": "13.67.8.224/28",
    "ip_type": "IPv4",
    "service": "AzureMachineLearning.SoutheastAsia",
    "region": "southeastasia"
  },
  {
    "ip_address": "20.43.128.112/28",
    "ip_type": "IPv4",
    "service": "AzureMachineLearning.SoutheastAsia",
    "region": "southeastasia"
  },
  {
    "ip_address": "20.195.69.64/28",
    "ip_type": "IPv4",
    "service": "AzureMachineLearning.SoutheastAsia",
    "region": "southeastasia"
  },
  {
    "ip_address": "23.98.82.192/28",
    "ip_type": "IPv4",
    "service": "AzureMachineLearning.SoutheastAsia",
    "region": "southeastasia"
  },
  {
    "ip_address": "40.78.234.128/28",
    "ip_type": "IPv4",
    "service": "AzureMachineLearning.SoutheastAsia",
    "region": "southeastasia"
  },
  {
    "ip_address": "40.90.184.249/32",
    "ip_type": "IPv4",
    "service": "AzureMachineLearning.SoutheastAsia",
    "region": "southeastasia"
  },
  {
    "ip_address": "52.230.56.136/32",
    "ip_type": "IPv4",
    "service": "AzureMachineLearning.SoutheastAsia",
    "region": "southeastasia"
  },
  {
    "ip_address": "2603:1040:5:1::2c0/122",
    "ip_type": "IPv6",
    "service": "AzureMachineLearning.SoutheastAsia",
    "region": "southeastasia"
  }
]