[
  {
    "ip_address": "20.38.133.4/30",
    "ip_type": "IPv4",
    "service": "ActionGroup.WestIndia",
    "region": "westindia"
  },
  {
    "ip_address": "20.207.175.176/30",
    "ip_type": "IPv4",
    "service": "ActionGroup.WestIndia",
    "region": "westindia"
  },
  {
    "ip_address": "2603:1040:806::10c/126",
    "ip_type": "IPv6",
    "service": "ActionGroup.WestIndia",
    "region": "westindia"
  },
  {
    "ip_address": "2603:1040:806:402::178/125",
    "ip_type": "IPv6",
    "service": "ActionGroup.WestIndia",
    "region": "westindia"
  }
]