[
  {
    "ip_address": "51.137.162.160/27",
    "ip_type": "IPv4",
    "service": "AzurePortal.UKWest",
    "region": "ukwest"
  },
  {
    "ip_address": "51.137.164.80/30",
    "ip_type": "IPv4",
    "service": "AzurePortal.UKWest",
    "region": "ukwest"
  },
  {
    "ip_address": "51.137.167.152/29",
    "ip_type": "IPv4",
    "service": "AzurePortal.UKWest",
    "region": "ukwest"
  },
  {
    "ip_address": "2603:1020:605::700/121",
    "ip_type": "IPv6",
    "service": "AzurePortal.UKWest",
    "region": "ukwest"
  }
]