[
  {
    "ip_address": "20.17.25.224/28",
    "ip_type": "IPv4",
    "service": "DataFactory.MalaysiaSouth",
    "region": "malaysiasouth"
  },
  {
    "ip_address": "20.17.26.192/26",
    "ip_type": "IPv4",
    "service": "DataFactory.MalaysiaSouth",
    "region": "malaysiasouth"
  },
  {
    "ip_address": "20.17.27.0/25",
    "ip_type": "IPv4",
    "service": "DataFactory.MalaysiaSouth",
    "region": "malaysiasouth"
  },
  {
    "ip_address": "20.17.56.0/23",
    "ip_type": "IPv4",
    "service": "DataFactory.MalaysiaSouth",
    "region": "malaysiasouth"
  },
  {
    "ip_address": "20.17.71.64/28",
    "ip_type": "IPv4",
    "service": "DataFactory.MalaysiaSouth",
    "region": "malaysiasouth"
  },
  {
    "ip_address": "2603:1040:1503:1::400/121",
    "ip_type": "IPv6",
    "service": "DataFactory.MalaysiaSouth",
    "region": "malaysiasouth"
  },
  {
    "ip_address": "2603:1040:1503:400::3c0/124",
    "ip_type": "IPv6",
    "service": "DataFactory.MalaysiaSouth",
    "region": "malaysiasouth"
  }
]