[
  {
    "ip_address": "20.37.71.64/26",
    "ip_type": "IPv4",
    "service": "Sql.UAECentral",
    "region": "uaecentral"
  },
  {
    "ip_address": "20.37.71.128/26",
    "ip_type": "IPv4",
    "service": "Sql.UAECentral",
    "region": "uaecentral"
  },
  {
    "ip_address": "20.37.72.64/27",
    "ip_type": "IPv4",
    "service": "Sql.UAECentral",
    "region": "uaecentral"
  },
  {
    "ip_address": "20.37.72.96/29",
    "ip_type": "IPv4",
    "service": "Sql.UAECentral",
    "region": "uaecentral"
  },
  {
    "ip_address": "20.37.73.64/27",
    "ip_type": "IPv4",
    "service": "Sql.UAECentral",
    "region": "uaecentral"
  },
  {
    "ip_address": "20.37.73.96/29",
    "ip_type": "IPv4",
    "service": "Sql.UAECentral",
    "region": "uaecentral"
  },
  {
    "ip_address": "20.203.95.128/25",
    "ip_type": "IPv4",
    "service": "Sql.UAECentral",
    "region": "uaecentral"
  },
  {
    "ip_address": "74.243.18.24/29",
    "ip_type": "IPv4",
    "service": "Sql.UAECentral",
    "region": "uaecentral"
  },
  {
    "ip_address": "74.243.20.128/27",
    "ip_type": "IPv4",
    "service": "Sql.UAECentral",
    "region": "uaecentral"
  },
  {
    "ip_address": "2603:1040:b04::280/123",
    "ip_type": "IPv6",
    "service": "Sql.UAECentral",
    "region": "uaecentral"
  },
  {
    "ip_address": "2603:1040:b04:1::200/121",
    "ip_type": "IPv6",
    "service": "Sql.UAECentral",
    "region": "uaecentral"
  },
  {
    "ip_address": "2603:1040:b04:5::600/121",
    "ip_type": "IPv6",
    "service": "Sql.UAECentral",
    "region": "uaecentral"
  },
  {
    "ip_address": "2603:1040:b04:400::/123",
    "ip_type": "IPv6",
    "service": "Sql.UAECentral",
    "region": "uaecentral"
  }
]