[
  {
    "ip_address": "20.153.19.0/24",
    "ip_type": "IPv4",
    "service": "Storage.BelgiumCentral",
    "region": "belgiumcentral"
  },
  {
    "ip_address": "20.153.20.0/24",
    "ip_type": "IPv4",
    "service": "Storage.BelgiumCentral",
    "region": "belgiumcentral"
  },
  {
    "ip_address": "57.150.194.0/23",
    "ip_type": "IPv4",
    "service": "Storage.BelgiumCentral",
    "region": "belgiumcentral"
  },
  {
    "ip_address": "57.150.196.0/23",
    "ip_type": "IPv4",
    "service": "Storage.BelgiumCentral",
    "region": "belgiumcentral"
  },
  {
    "ip_address": "57.150.198.0/24",
    "ip_type": "IPv4",
    "service": "Storage.BelgiumCentral",
    "region": "belgiumcentral"
  },
  {
    "ip_address": "2603:1020:1503::/48",
    "ip_type": "IPv6",
    "service": "Storage.BelgiumCentral",
    "region": "belgiumcentral"
  }
]