[
  {
    "ip_address": "13.70.74.192/27",
    "ip_type": "IPv4",
    "service": "AzureIoTHub.AustraliaEast",
    "region": "australiaeast"
  },
  {
    "ip_address": "20.37.198.160/27",
    "ip_type": "IPv4",
    "service": "AzureIoTHub.AustraliaEast",
    "region": "australiaeast"
  },
  {
    "ip_address": "20.37.199.0/25",
    "ip_type": "IPv4",
    "service": "AzureIoTHub.AustraliaEast",
    "region": "australiaeast"
  },
  {
    "ip_address": "40.79.163.32/27",
    "ip_type": "IPv4",
    "service": "AzureIoTHub.AustraliaEast",
    "region": "australiaeast"
  },
  {
    "ip_address": "40.79.171.128/27",
    "ip_type": "IPv4",
    "service": "AzureIoTHub.AustraliaEast",
    "region": "australiaeast"
  },
  {
    "ip_address": "52.147.10.141/32",
    "ip_type": "IPv4",
    "service": "AzureIoTHub.AustraliaEast",
    "region": "australiaeast"
  },
  {
    "ip_address": "52.147.10.149/32",
    "ip_type": "IPv4",
    "service": "AzureIoTHub.AustraliaEast",
    "region": "australiaeast"
  },
  {
    "ip_address": "104.210.105.7/32",
    "ip_type": "IPv4",
    "service": "AzureIoTHub.AustraliaEast",
    "region": "australiaeast"
  },
  {
    "ip_address": "2603:1010:6:402::300/123",
    "ip_type": "IPv6",
    "service": "AzureIoTHub.AustraliaEast",
    "region": "australiaeast"
  },
  {
    "ip_address": "2603:1010:6:802::240/123",
    "ip_type": "IPv6",
    "service": "AzureIoTHub.AustraliaEast",
    "region": "australiaeast"
  },
  {
    "ip_address": "2603:1010:6:c02::240/123",
    "ip_type": "IPv6",
    "service": "AzureIoTHub.AustraliaEast",
    "region": "australiaeast"
  }
]