[
  {
    "ip_address": "20.36.108.160/27",
    "ip_type": "IPv4",
    "service": "AzureIoTHub.AustraliaCentral",
    "region": "australiacentral"
  },
  {
    "ip_address": "20.37.227.64/27",
    "ip_type": "IPv4",
    "service": "AzureIoTHub.AustraliaCentral",
    "region": "australiacentral"
  },
  {
    "ip_address": "20.37.227.128/25",
    "ip_type": "IPv4",
    "service": "AzureIoTHub.AustraliaCentral",
    "region": "australiacentral"
  },
  {
    "ip_address": "2603:1010:304:402::300/123",
    "ip_type": "IPv6",
    "service": "AzureIoTHub.AustraliaCentral",
    "region": "australiacentral"
  }
]