[
  {
    "ip_address": "4.240.148.184/29",
    "ip_type": "IPv4",
    "service": "PowerQueryOnline.JioIndiaCentral",
    "region": "jioindiacentral"
  },
  {
    "ip_address": "20.192.225.32/31",
    "ip_type": "IPv4",
    "service": "PowerQueryOnline.JioIndiaCentral",
    "region": "jioindiacentral"
  },
  {
    "ip_address": "20.207.2.166/31",
    "ip_type": "IPv4",
    "service": "PowerQueryOnline.JioIndiaCentral",
    "region": "jioindiacentral"
  },
  {
    "ip_address": "20.207.2.168/29",
    "ip_type": "IPv4",
    "service": "PowerQueryOnline.JioIndiaCentral",
    "region": "jioindiacentral"
  },
  {
    "ip_address": "2603:1040:1104::200/123",
    "ip_type": "IPv6",
    "service": "PowerQueryOnline.JioIndiaCentral",
    "region": "jioindiacentral"
  },
  {
    "ip_address": "2603:1040:1104:400::168/125",
    "ip_type": "IPv6",
    "service": "PowerQueryOnline.JioIndiaCentral",
    "region": "jioindiacentral"
  }
]